ZetcodeTuxingJiaochengChuyiFix1/README.md
ZetcodeTuxingJiaochengChuyiFix1/__init__.py
ZetcodeTuxingJiaochengChuyiFix1/__main__.py
ZetcodeTuxingJiaochengChuyiFix1/file.epub
ZetcodeTuxingJiaochengChuyiFix1/index.html
ZetcodeTuxingJiaochengChuyiFix1/css/__init__.py
ZetcodeTuxingJiaochengChuyiFix1/css/annotations.css
ZetcodeTuxingJiaochengChuyiFix1/css/main.css
ZetcodeTuxingJiaochengChuyiFix1/css/normalize.css
ZetcodeTuxingJiaochengChuyiFix1/css/popup.css
ZetcodeTuxingJiaochengChuyiFix1/font/__init__.py
ZetcodeTuxingJiaochengChuyiFix1/font/fontello.eot
ZetcodeTuxingJiaochengChuyiFix1/font/fontello.svg
ZetcodeTuxingJiaochengChuyiFix1/font/fontello.ttf
ZetcodeTuxingJiaochengChuyiFix1/font/fontello.woff
ZetcodeTuxingJiaochengChuyiFix1/img/__init__.py
ZetcodeTuxingJiaochengChuyiFix1/img/annotator-glyph-sprite.png
ZetcodeTuxingJiaochengChuyiFix1/img/annotator-icon-sprite.png
ZetcodeTuxingJiaochengChuyiFix1/img/apple-touch-icon.png
ZetcodeTuxingJiaochengChuyiFix1/img/cancelfullscreen.png
ZetcodeTuxingJiaochengChuyiFix1/img/close.png
ZetcodeTuxingJiaochengChuyiFix1/img/fullscreen.png
ZetcodeTuxingJiaochengChuyiFix1/img/loader.gif
ZetcodeTuxingJiaochengChuyiFix1/img/menu-icon.png
ZetcodeTuxingJiaochengChuyiFix1/img/save.png
ZetcodeTuxingJiaochengChuyiFix1/img/saved.png
ZetcodeTuxingJiaochengChuyiFix1/img/settings-s.png
ZetcodeTuxingJiaochengChuyiFix1/img/settings.png
ZetcodeTuxingJiaochengChuyiFix1/img/star.png
ZetcodeTuxingJiaochengChuyiFix1/js/__init__.py
ZetcodeTuxingJiaochengChuyiFix1/js/epub.js
ZetcodeTuxingJiaochengChuyiFix1/js/epub.min.js
ZetcodeTuxingJiaochengChuyiFix1/js/epub.min.map
ZetcodeTuxingJiaochengChuyiFix1/js/hooks.min.js
ZetcodeTuxingJiaochengChuyiFix1/js/hooks.min.map
ZetcodeTuxingJiaochengChuyiFix1/js/reader.js
ZetcodeTuxingJiaochengChuyiFix1/js/reader.js.map
ZetcodeTuxingJiaochengChuyiFix1/js/reader.min.js
ZetcodeTuxingJiaochengChuyiFix1/js/reader.min.map
ZetcodeTuxingJiaochengChuyiFix1/js/hooks/__init__.py
zetcode_tuxing_jiaocheng_chuyi_fix1-2025.3.24.1.dist-info/METADATA
zetcode_tuxing_jiaocheng_chuyi_fix1-2025.3.24.1.dist-info/WHEEL
zetcode_tuxing_jiaocheng_chuyi_fix1-2025.3.24.1.dist-info/entry_points.txt
zetcode_tuxing_jiaocheng_chuyi_fix1-2025.3.24.1.dist-info/top_level.txt
zetcode_tuxing_jiaocheng_chuyi_fix1-2025.3.24.1.dist-info/RECORD
